persica/__init__.py
persica/application.py
persica/applicationbuilder.py
persica/error.py
persica/context/__init__.py
persica/context/application.py
persica/factory/__init__.py
persica/factory/abstract.py
persica/factory/component.py
persica/factory/definition.py
persica/factory/interface.py
persica/factory/registry.py
persica/scanner/__init__.py
persica/scanner/graph.py
persica/scanner/path.py
persica/scanner/visitor.py
persica/utils/__init__.py
persica/utils/logging.py
persica-0.1.0a5.dist-info/METADATA
persica-0.1.0a5.dist-info/WHEEL
persica-0.1.0a5.dist-info/RECORD
