Metadata-Version: 2.3
Name: persica
Version: 0.1.0a5
Summary: Automatic framework for Pythone
Author-email: luoshuijs <luoshuijs@outlook.com>
Requires-Python: >=3.10
Requires-Dist: networkx>=3.3
